LICENSE.txt
MANIFEST.in
README.rst
setup.py
examples/honeycomb/honeycomb_200_200.log
examples/honeycomb/magnetism.png
examples/honeycomb/specific_heat.png
examples/honeycomb/susceptibility.png
examples/square/magnetism.png
examples/square/specific_heat.png
examples/square/square_200_200.log
examples/square/susceptibility.png
examples/triangular/magnetism.png
examples/triangular/specific_heat.png
examples/triangular/susceptibility.png
examples/triangular/triangular_200_200.log
spins2cpu/__init__.py
spins2cpu/functions.py
spins2cpu/plots.py
spins2cpu/sample.py
spins2cpu/wrapper.py
spins2cpu.egg-info/PKG-INFO
spins2cpu.egg-info/SOURCES.txt
spins2cpu.egg-info/dependency_links.txt
spins2cpu.egg-info/entry_points.txt
spins2cpu.egg-info/requires.txt
spins2cpu.egg-info/top_level.txt
spins2cpu/ising/__init__.py
spins2cpu/ising/ammm.py
spins2cpu/ising/ammm_update.py
spins2cpu/ising/c2m.py
spins2cpu/ising/c2m_update.py
spins2cpu/ising/centered_rectangular.py
spins2cpu/ising/centered_rectangular_update.py
spins2cpu/ising/cubic.py
spins2cpu/ising/cubic_update.py
spins2cpu/ising/honeycomb.py
spins2cpu/ising/honeycomb_update.py
spins2cpu/ising/i_p6mmm.py
spins2cpu/ising/i_p6mmm_update.py
spins2cpu/ising/kagome.py
spins2cpu/ising/kagome_update.py
spins2cpu/ising/p3m1.py
spins2cpu/ising/p3m1_update.py
spins2cpu/ising/p6mmm.py
spins2cpu/ising/p6mmm_update.py
spins2cpu/ising/rectangular.py
spins2cpu/ising/rectangular_update.py
spins2cpu/ising/square.py
spins2cpu/ising/square_update.py
spins2cpu/ising/triangular.py
spins2cpu/ising/triangular_update.py
spins2cpu/mae/__init__.py
spins2cpu/mae/c2m.py
spins2cpu/mae/c2m_update.py
spins2cpu/mae/centered_rectangular.py
spins2cpu/mae/centered_rectangular_update.py
spins2cpu/mae/rectangular.py
spins2cpu/mae/rectangular_update.py
spins2cpu/mae/square.py
spins2cpu/mae/square_update.py
spins2cpu/mae/triangular.py
spins2cpu/mae/triangular_update.py
spins2cpu/single/__init__.py
spins2cpu/single/c2m.py
spins2cpu/single/c2m_update.py
spins2cpu/single/centered_rectangular.py
spins2cpu/single/centered_rectangular_update.py
spins2cpu/single/honeycomb.py
spins2cpu/single/honeycomb_update.py
spins2cpu/single/i_p6mmm.py
