Metadata-Version: 2.1
Name: spins2cpu
Version: 0.1.5.1
Summary: spins2cpu: A Monte Carlo Simulation Code for the Phase Transition in 2D/3D Materials
Home-page: https://github.com/lkccrr/spins2cpu
Author: kan
Author-email: luokan@hrbeu.edu.cn
License: MIT
Keywords: Monte Carlo Simulation Ising Model
Platform: Unix
Platform: Windows
Classifier: License :: OSI Approved :: MIT License
Classifier: Programming Language :: Python
Classifier: Programming Language :: Python :: 3
Classifier: Programming Language :: Python :: 3 :: Only
Classifier: Programming Language :: Python :: 3.6
Classifier: Programming Language :: Python :: 3.7
Classifier: Programming Language :: Python :: 3.8
Classifier: Programming Language :: Python :: 3.9
Classifier: Programming Language :: Python :: 3.10
Classifier: Programming Language :: Python :: 3.11
Requires-Python: >=3.6
